{
  "bulletin_metadata": {
    "issue_number": "7118",
    "publication_year_description": "Cent-onzième année",
    "date_hijri": "20 moharrem 1444",
    "date_gregorian": "2022-08-18",
    "issn": "0851-1217"
  },
  "table_of_contents": [],
  "legal_texts": [
    {
      "type": "Loi",
      "number": "40-17",
      "title": "portant statut de Bank Al-Maghrib promulguée par le Dahir n° 1-19-82 du 17 chaoual 1440 (21 juin 2019), j'ai l'honneur de présenter à Votre Majesté le rapport concernant l'année 2021, soixante-troisième exercice de l'Institut d'émission",
      "publication_date_hijri": "",
      "publication_date_gregorian": "",
      "page_start": 1080,
      "description": "Loi n° 40-17 portant statut de Bank Al-Maghrib promulguée par le Dahir n° 1-19-82 du 17 chaoual 1440 (21 juin 2019), j'ai l'honneur de présenter à Votre Majesté le rapport concernant l'année 2021, soixante-troisième exercice de l'Institut d'émission, d'un montant de 82,00 dirhams, conclu le 8 décembre 2021",
      "signatories": [
        {
          "name": "ETATS FINANCIERS DE LA BANQUE",
          "title": ""
        }
      ],
      "content_details": {
        "loan_guarantee": {
          "amount": 82.0,
          "currency": "D",
          "beneficiary": "Ministère de l"
        }
      }
    },
    {
      "type": "Loi",
      "number": "32-10",
      "title": "précitée s'est élevée, pour sa part, à 262 KDH (Cf",
      "publication_date_hijri": "",
      "publication_date_gregorian": "",
      "page_start": 1322,
      "description": "Loi n° 32-10 précitée s'est élevée, pour sa part, à 262 KDH (Cf, d'un montant de 3.235,00 dirhams",
      "signatories": [
        {
          "name": "MASI MADEX",
          "title": ""
        }
      ],
      "content_details": {
        "loan_guarantee": {
          "amount": 3235.0,
          "currency": "D",
          "beneficiary": "Ministère de l"
        }
      }
    }
  ]
}