{
  "bulletin_metadata": {
    "issue_number": "7366",
    "publication_year_description": "Cent-quatorzième année",
    "date_hijri": "5 chaoual 1439",
    "date_gregorian": "2018-06-19",
    "issn": "0851-1217"
  },
  "table_of_contents": [],
  "legal_texts": [
    {
      "type": "Décret",
      "number": "2-24-966",
      "title": "du 3 joumada II 1446",
      "publication_date_hijri": "",
      "publication_date_gregorian": "",
      "page_start": 0,
      "description": "Décret n° 2-24-966 du 3 joumada II 1446, d'un montant de 966,00 dirhams",
      "signatories": [],
      "content_details": {
        "loan_guarantee": {
          "amount": 966.0,
          "currency": "D"
        }
      }
    },
    {
      "type": "Décret",
      "number": "",
      "title": "n° 2-17-743 du 5 chaoual 1439 (19 juin 2018) fixant les activités exercées par les sociétés industrielles bénéficiant de l'exonération temporaire de l'impôt sur les sociétés prévue à l'article 6 (II-B-4°) du code général des impôts",
      "publication_date_hijri": "",
      "publication_date_gregorian": "",
      "page_start": 0,
      "description": "Décret n° 2-17-743 du 5 chaoual 1439 (19 juin 2018) fixant les activités exercées par les sociétés industrielles bénéficiant de l'exonération temporaire de l'impôt sur les sociétés prévue à l'article 6 (II-B-4°) du code général des impôts, d'un montant de 743,00 dirhams",
      "signatories": [],
      "content_details": {
        "loan_guarantee": {
          "amount": 743.0,
          "currency": "D"
        }
      }
    },
    {
      "type": "Décret",
      "number": "2-24-1110",
      "title": "du 25 joumada II 1446",
      "publication_date_hijri": "",
      "publication_date_gregorian": "",
      "page_start": 0,
      "description": "Décret n° 2-24-1110 du 25 joumada II 1446, d'un montant de 1.110,00 dirhams",
      "signatories": [],
      "content_details": {
        "loan_guarantee": {
          "amount": 1110.0,
          "currency": "D"
        }
      }
    },
    {
      "type": "Décret",
      "number": "2-06-574",
      "title": "du 10 hija 1427 (31 décembre",
      "publication_date_hijri": "",
      "publication_date_gregorian": "",
      "page_start": 0,
      "description": "Décret n° 2-06-574 du 10 hija 1427 (31 décembre, d'un montant de 574,00 dirhams",
      "signatories": [
        {
          "name": "AZIZ AKHANNOUCH",
          "title": ""
        },
        {
          "name": "FOUZI LEKJAA",
          "title": ""
        }
      ],
      "content_details": {
        "loan_guarantee": {
          "amount": 574.0,
          "currency": "D"
        }
      }
    },
    {
      "type": "Décret",
      "number": "2-24-1006",
      "title": "du 26 joumada I 1446 (29 novembre 2024)",
      "publication_date_hijri": "",
      "publication_date_gregorian": "",
      "page_start": 10,
      "description": "Décret n° 2-24-1006 du 26 joumada I 1446 (29 novembre 2024), d'un montant de 1.006,00 dirhams",
      "signatories": [
        {
          "name": "AZIZ AKHANNOUCH",
          "title": ""
        },
        {
          "name": "FOUZI LEKJAA",
          "title": ""
        }
      ],
      "content_details": {
        "loan_guarantee": {
          "amount": 1006.0,
          "currency": "D"
        }
      }
    },
    {
      "type": "Décret",
      "number": "2-24-1007",
      "title": "du 26 joumada I 1446 (29 novembre 2024)",
      "publication_date_hijri": "",
      "publication_date_gregorian": "",
      "page_start": 10,
      "description": "Décret n° 2-24-1007 du 26 joumada I 1446 (29 novembre 2024), d'un montant de 1.007,00 dirhams, conclu le 23 rabii",
      "signatories": [
        {
          "name": "AZIZ AKHANNOUCH",
          "title": ""
        },
        {
          "name": "FOUZI LEKJAA",
          "title": ""
        }
      ],
      "content_details": {
        "loan_guarantee": {
          "amount": 1007.0,
          "currency": "D"
        }
      }
    },
    {
      "type": "Décret",
      "number": "2-24-1048",
      "title": "du 26 joumada I 1446 (29 novembre 2024)",
      "publication_date_hijri": "",
      "publication_date_gregorian": "",
      "page_start": 10,
      "description": "Décret n° 2-24-1048 du 26 joumada I 1446 (29 novembre 2024), d'un montant de douze millions d'euros (12.000.000,00 dirhams), conclu le 12 novembre 2024 avec KfW",
      "signatories": [
        {
          "name": "FOUZI LEKJAA",
          "title": ""
        }
      ],
      "content_details": {
        "loan_guarantee": {
          "amount": 12000000.0,
          "currency": "D",
          "lender": "KfW"
        }
      }
    },
    {
      "type": "Décret",
      "number": "2-24-1055",
      "title": "du 26 joumada I 1446 (29 novembre 2024)",
      "publication_date_hijri": "",
      "publication_date_gregorian": "",
      "page_start": 12,
      "description": "Décret n° 2-24-1055 du 26 joumada I 1446 (29 novembre 2024), d'un montant de cinq cents millions d'euros (500.000.000,00 euros)",
      "signatories": [
        {
          "name": "AZIZ AKHANNOUCH",
          "title": ""
        },
        {
          "name": "FOUZI LEKJAA",
          "title": ""
        }
      ],
      "content_details": {
        "loan_guarantee": {
          "amount": 500000000.0,
          "currency": "EUR",
          "lender": "Banque européenne d'investissement"
        }
      }
    },
    {
      "type": "Décret",
      "number": "2-24-1097",
      "title": "du 10 joumada II 1446 (12 décembre 2024)",
      "publication_date_hijri": "",
      "publication_date_gregorian": "",
      "page_start": 12,
      "description": "Décret n° 2-24-1097 du 10 joumada II 1446 (12 décembre 2024), d'un montant de cinquante millions d'euros (50.000.000,00 dirhams), conclu le 27 novembre 2024",
      "signatories": [
        {
          "name": "AZIZ AKHANNOUCH",
          "title": ""
        },
        {
          "name": "FOUZI LEKJAA",
          "title": ""
        }
      ],
      "content_details": {
        "loan_guarantee": {
          "amount": 50000000.0,
          "currency": "D"
        }
      }
    },
    {
      "type": "Décret",
      "number": "2-24-1098",
      "title": "du 10 joumada II 1446 (12 décembre 2024)",
      "publication_date_hijri": "",
      "publication_date_gregorian": "",
      "page_start": 12,
      "description": "Décret n° 2-24-1098 du 10 joumada II 1446 (12 décembre 2024), d'un montant de cent millions d'euros (100.000.000,00 dirhams), conclu le 27 novembre 2024",
      "signatories": [
        {
          "name": "AZIZ AKHANNOUCH",
          "title": ""
        },
        {
          "name": "FOUZI LEKJAA",
          "title": ""
        }
      ],
      "content_details": {
        "loan_guarantee": {
          "amount": 100000000.0,
          "currency": "D"
        }
      }
    },
    {
      "type": "Décret",
      "number": "2-24-1095",
      "title": "du 24 joumada II 1446 (26 décembre 2024)",
      "publication_date_hijri": "",
      "publication_date_gregorian": "",
      "page_start": 12,
      "description": "Décret n° 2-24-1095 du 24 joumada II 1446 (26 décembre 2024), d'un montant de cent vingt millions d'euros (120.000.000,00 dirhams), conclu le 22 novembre 2024",
      "signatories": [
        {
          "name": "et des finances",
          "title": "La ministre de l'économie"
        },
        {
          "name": "AZIZ AKHANNOUCH",
          "title": ""
        }
      ],
      "content_details": {
        "loan_guarantee": {
          "amount": 120000000.0,
          "currency": "D"
        }
      }
    },
    {
      "type": "Décret",
      "number": "2-23-971",
      "title": "du 24 joumada I 1446",
      "publication_date_hijri": "",
      "publication_date_gregorian": "",
      "page_start": 12,
      "description": "Décret n° 2-23-971 du 24 joumada I 1446, d'un montant de 971,00 dirhams, conclu le 19 moharrem 1446, au profit de Office national \ndes hydrocarbures et des mines et",
      "signatories": [
        {
          "name": "AVIS ET COMMUNICATIONS",
          "title": ""
        }
      ],
      "content_details": {
        "loan_guarantee": {
          "amount": 971.0,
          "currency": "D"
        }
      }
    },
    {
      "type": "Décret",
      "number": "2-17-743",
      "title": "du 5 chaoual 1439 (19 juin 2018)",
      "publication_date_hijri": "",
      "publication_date_gregorian": "",
      "page_start": 0,
      "description": "Décret n° 2-17-743 du 5 chaoual 1439 (19 juin 2018), d'un montant de 743,00 dirhams",
      "signatories": [
        {
          "name": "FOUZI LEKJAA",
          "title": ""
        }
      ],
      "content_details": {
        "loan_guarantee": {
          "amount": 743.0,
          "currency": "D"
        }
      }
    },
    {
      "type": "Loi",
      "number": "52-20",
      "title": "portant création de l'Agence nationale des eaux et forêts, promulguée par le dahir n° 1-21-71 du 3 hija 1442 (14 juillet 2021), notamment son article 5 ;",
      "publication_date_hijri": "",
      "publication_date_gregorian": "",
      "page_start": 12,
      "description": "Loi n° 52-20 portant création de l'Agence nationale des eaux et forêts, promulguée par le dahir n° 1-21-71 du 3 hija 1442 (14 juillet 2021), notamment son article 5 ;, d'un montant de 71,00 dirhams",
      "signatories": [],
      "content_details": {
        "loan_guarantee": {
          "amount": 71.0,
          "currency": "D"
        }
      }
    },
    {
      "type": "Décret",
      "number": "2-23-970",
      "title": "du 10 ramadan 1445 (21 mars",
      "publication_date_hijri": "",
      "publication_date_gregorian": "",
      "page_start": 12,
      "description": "Décret n° 2-23-970 du 10 ramadan 1445 (21 mars, d'un montant de 970,00 dirhams",
      "signatories": [
        {
          "name": "Le ministre de l'agriculture",
          "title": ":"
        },
        {
          "name": "AZIZ AKHANNOUCH",
          "title": ""
        },
        {
          "name": "AHMED EL BOUARI",
          "title": ""
        }
      ],
      "content_details": {
        "loan_guarantee": {
          "amount": 970.0,
          "currency": "D"
        }
      }
    },
    {
      "type": "Décret",
      "number": "2-14-652",
      "title": "du 8 safar 1436 (1er décembre 2014)",
      "publication_date_hijri": "",
      "publication_date_gregorian": "",
      "page_start": 14,
      "description": "Décret n° 2-14-652 du 8 safar 1436 (1er décembre 2014), d'un montant de 652,00 dirhams",
      "signatories": [],
      "content_details": {
        "loan_guarantee": {
          "amount": 652.0,
          "currency": "D"
        }
      }
    },
    {
      "type": "Loi",
      "number": "104-12",
      "title": "sur la liberté des",
      "publication_date_hijri": "",
      "publication_date_gregorian": "",
      "page_start": 14,
      "description": "Loi n° 104-12 sur la liberté des",
      "signatories": []
    },
    {
      "type": "Décret",
      "number": "2-21-829",
      "title": "du 14 rabii I 1443 (21 octobre 2021)",
      "publication_date_hijri": "",
      "publication_date_gregorian": "",
      "page_start": 14,
      "description": "Décret n° 2-21-829 du 14 rabii I 1443 (21 octobre 2021), d'un montant de 829,00 dirhams, conclu le 5 chaabane 1445, au profit de Office national des hydrocarbures \net des mines et",
      "signatories": [
        {
          "name": "LEILA BENALI",
          "title": ""
        }
      ],
      "content_details": {
        "loan_guarantee": {
          "amount": 829.0,
          "currency": "D",
          "beneficiary": "Office national des hydrocarbures \net des mines et"
        }
      }
    },
    {
      "type": "Décret",
      "number": "2-03-199",
      "title": "du 20 rabii I 1424 (22 mai 2003)",
      "publication_date_hijri": "",
      "publication_date_gregorian": "",
      "page_start": 14,
      "description": "Décret n° 2-03-199 du 20 rabii I 1424 (22 mai 2003), d'un montant de 199,00 dirhams",
      "signatories": [],
      "content_details": {
        "loan_guarantee": {
          "amount": 199.0,
          "currency": "D"
        }
      }
    },
    {
      "type": "Loi",
      "number": "46-02",
      "title": "relative au régime des",
      "publication_date_hijri": "",
      "publication_date_gregorian": "",
      "page_start": 14,
      "description": "Loi n° 46-02 relative au régime des",
      "signatories": []
    },
    {
      "type": "Décret",
      "number": "2-17-642",
      "title": "",
      "publication_date_hijri": "",
      "publication_date_gregorian": "",
      "page_start": 14,
      "description": "Décret n° 2-17-642",
      "signatories": []
    },
    {
      "type": "Loi",
      "number": "21-90",
      "title": "susvisée, tel qu'il a été modifié et complété, notamment son",
      "publication_date_hijri": "",
      "publication_date_gregorian": "",
      "page_start": 28,
      "description": "Loi n° 21-90 susvisée, tel qu'il a été modifié et complété, notamment son, d'un montant de 19,00 dirhams, conclu le 19 moharrem 1446, au profit de Office national des \nhydrocarbures et des mines et",
      "signatories": [],
      "content_details": {
        "loan_guarantee": {
          "amount": 118.0,
          "currency": "D"
        }
      }
    },
    {
      "type": "Loi",
      "number": "33-01",
      "title": "portant création de l'Office national des hydrocarbures et des mines promulguée par le dahir n° 1-03-203 du 16 ramadan 1424 (11 novembre 2003) ;",
      "publication_date_hijri": "",
      "publication_date_gregorian": "",
      "page_start": 26,
      "description": "Loi n° 33-01 portant création de l'Office national des hydrocarbures et des mines promulguée par le dahir n° 1-03-203 du 16 ramadan 1424 (11 novembre 2003) ;, d'un montant de 203,00 dirhams, au profit de Office national des \nhydrocarbures et des mines",
      "signatories": [],
      "content_details": {
        "loan_guarantee": {
          "amount": 203.0,
          "currency": "D",
          "beneficiary": "Office national des \nhydrocarbures et des mines"
        }
      }
    },
    {
      "type": "Décret",
      "number": "2-93-786",
      "title": "du 18 joumada I 1414 (3 novembre 1993)",
      "publication_date_hijri": "",
      "publication_date_gregorian": "",
      "page_start": 26,
      "description": "Décret n° 2-93-786 du 18 joumada I 1414 (3 novembre 1993), d'un montant de 786,00 dirhams",
      "signatories": [],
      "content_details": {
        "loan_guarantee": {
          "amount": 786.0,
          "currency": "D"
        }
      }
    },
    {
      "type": "Loi",
      "number": "27-99",
      "title": "promulguée par le dahir n° 1-99-340 du 9 kaada 1420 (15 février 2000), notamment ses articles 4 et 34 ;",
      "publication_date_hijri": "",
      "publication_date_gregorian": "",
      "page_start": 30,
      "description": "Loi n° 27-99 promulguée par le dahir n° 1-99-340 du 9 kaada 1420 (15 février 2000), notamment ses articles 4 et 34 ;, d'un montant de 340,00 dirhams",
      "signatories": [],
      "content_details": {
        "loan_guarantee": {
          "amount": 340.0,
          "currency": "D"
        }
      }
    },
    {
      "type": "Décret",
      "number": "",
      "title": "n° 2-99-210 du 9 hija 1420 (16 mars 2000), notamment son",
      "publication_date_hijri": "",
      "publication_date_gregorian": "",
      "page_start": 30,
      "description": "Décret n° 2-99-210 du 9 hija 1420 (16 mars 2000), notamment son, d'un montant de 210,00 dirhams",
      "signatories": [],
      "content_details": {
        "loan_guarantee": {
          "amount": 210.0,
          "currency": "D"
        }
      }
    },
    {
      "type": "Décret",
      "number": "2-04-372",
      "title": "du 16 kaada 1425 (29 décembre 2004)",
      "publication_date_hijri": "",
      "publication_date_gregorian": "",
      "page_start": 30,
      "description": "Décret n° 2-04-372 du 16 kaada 1425 (29 décembre 2004), d'un montant de 372,00 dirhams, conclu le 5 chaabane 1445, au profit de Office national des hydrocarbures et \ndes mines et les",
      "signatories": [
        {
          "name": "LEILA BENALI",
          "title": ""
        },
        {
          "name": "NADIA FETTAH",
          "title": ""
        }
      ],
      "content_details": {
        "loan_guarantee": {
          "amount": 372.0,
          "currency": "D",
          "beneficiary": "Office national des hydrocarbures et des mines et \nles"
        }
      }
    },
    {
      "type": "Loi",
      "number": "24-09",
      "title": "relative à la sécurité des produits et des services et complétant le dahir du 9 ramadan 1331 (12 août 1913) formant code des obligations et des contrats, notamment ses articles 4 et 5 ;",
      "publication_date_hijri": "",
      "publication_date_gregorian": "",
      "page_start": 30,
      "description": "Loi n° 24-09 relative à la sécurité des produits et des services et complétant le dahir du 9 ramadan 1331 (12 août 1913) formant code des obligations et des contrats, notamment ses articles 4 et 5 ;, d'un montant de 13,00 dirhams",
      "signatories": [],
      "content_details": {
        "loan_guarantee": {
          "amount": 13.0,
          "currency": "D"
        }
      }
    },
    {
      "type": "Décret",
      "number": "2-12-502",
      "title": "du 2 rejeb 1434 (13 mai 2013) pris",
      "publication_date_hijri": "",
      "publication_date_gregorian": "",
      "page_start": 30,
      "description": "Décret n° 2-12-502 du 2 rejeb 1434 (13 mai 2013) pris, d'un montant de 502,00 dirhams",
      "signatories": [],
      "content_details": {
        "loan_guarantee": {
          "amount": 502.0,
          "currency": "D"
        }
      }
    },
    {
      "type": "Loi",
      "number": "25-08",
      "title": "portant création de l'Office national de sécurité sanitaire des produits alimentaires, promulguée par le dahir n°1-09-20 du 22 safar 1430 (18 février 2009), notamment son article 2 ;",
      "publication_date_hijri": "",
      "publication_date_gregorian": "",
      "page_start": 34,
      "description": "Loi n° 25-08 portant création de l'Office national de sécurité sanitaire des produits alimentaires, promulguée par le dahir n°1-09-20 du 22 safar 1430 (18 février 2009), notamment son article 2 ;, d'un montant de 20,00 dirhams, au profit de Office national de",
      "signatories": [
        {
          "name": "AHMED EL BOUARI",
          "title": ""
        }
      ],
      "content_details": {
        "loan_guarantee": {
          "amount": 20.0,
          "currency": "D",
          "beneficiary": "Office national de"
        }
      }
    },
    {
      "type": "Décret",
      "number": "2-24-991",
      "title": "du 24 rabii II 1446 (28 octobre",
      "publication_date_hijri": "",
      "publication_date_gregorian": "",
      "page_start": 48,
      "description": "Décret n° 2-24-991 du 24 rabii II 1446 (28 octobre, d'un montant de 991,00 dirhams",
      "signatories": [
        {
          "name": "FAITS FAITS MARQUANTS MARQUANTS",
          "title": ""
        }
      ],
      "content_details": {
        "loan_guarantee": {
          "amount": 991.0,
          "currency": "D"
        }
      }
    },
    {
      "type": "Loi",
      "number": "64-12",
      "title": "» La Commission de discipline est présidée par le magistrat de la Cour de Cassation, membre du Conseil",
      "publication_date_hijri": "",
      "publication_date_gregorian": "",
      "page_start": 110,
      "description": "Loi n° 64-12 » La Commission de discipline est présidée par le magistrat de la Cour de Cassation, membre du Conseil, d'un montant de 7.363,00 dirhams",
      "signatories": [],
      "content_details": {
        "loan_guarantee": {
          "amount": 7363.0,
          "currency": "D",
          "beneficiary": "ministère de l"
        }
      }
    },
    {
      "type": "Loi",
      "number": "69-21",
      "title": "modifiant la",
      "publication_date_hijri": "",
      "publication_date_gregorian": "",
      "page_start": 56,
      "description": "Loi n° 69-21 modifiant la",
      "signatories": []
    },
    {
      "type": "Loi",
      "number": "15-95",
      "title": "formant Code du Commerce en ce qui concerne les délais",
      "publication_date_hijri": "",
      "publication_date_gregorian": "",
      "page_start": 56,
      "description": "Loi n° 15-95 formant Code du Commerce en ce qui concerne les délais, d'un montant de 8,00 dirhams",
      "signatories": [],
      "content_details": {
        "loan_guarantee": {
          "amount": 8.0,
          "currency": "D"
        }
      }
    },
    {
      "type": "Loi",
      "number": "17-99",
      "title": "portant code des assurances. Pour rappel, lesdits projets visent notamment à intégrer la mission de contribution à la stabilité financière 70 BULLETIN OFFICIEL Nº 7366 - 1er rejeb 1446 (2-1-2025) parmi les missions dévolues à l'Autorité et à la doter des pouvoirs en matière de supervision macroprudentielle",
      "publication_date_hijri": "",
      "publication_date_gregorian": "",
      "page_start": 68,
      "description": "Loi n° 17-99 portant code des assurances. Pour rappel, lesdits projets visent notamment à intégrer la mission de contribution à la stabilité financière 70 BULLETIN OFFICIEL Nº 7366 - 1er rejeb 1446 (2-1-2025) parmi les missions dévolues à l'Autorité et à la doter des pouvoirs en matière de supervision macroprudentielle, d'un montant de 162,00 dirhams avec AFD",
      "signatories": [],
      "content_details": {
        "loan_guarantee": {
          "amount": 39.0,
          "currency": "D"
        }
      }
    },
    {
      "type": "Décret",
      "number": "2-18-1009",
      "title": "du 23 chaabane 1440 (29",
      "publication_date_hijri": "",
      "publication_date_gregorian": "",
      "page_start": 56,
      "description": "Décret n° 2-18-1009 du 23 chaabane 1440 (29, d'un montant de 1.009,00 dirhams",
      "signatories": [],
      "content_details": {
        "loan_guarantee": {
          "amount": 1009.0,
          "currency": "D"
        }
      }
    },
    {
      "type": "Décret",
      "number": "2-18-785",
      "title": "du 29 avril 2019 pris pour l'application",
      "publication_date_hijri": "",
      "publication_date_gregorian": "",
      "page_start": 58,
      "description": "Décret n° 2-18-785 du 29 avril 2019 pris pour l'application, d'un montant de 785,00 dirhams",
      "signatories": [],
      "content_details": {
        "loan_guarantee": {
          "amount": 785.0,
          "currency": "D"
        }
      }
    },
    {
      "type": "Loi",
      "number": "110-14",
      "title": "instituant un régime de couverture des conséquences d'événements catastrophiques ; » La demande d'approbation du projet de modification du règlement de la caisse interne de décès de la Mutuelle Générale du Personnel des Administrations Publiques (MGPAP) ; » Le projet d'amendement de l'arrêté pris en application du livre II du code des assurances ; » La demande de changement de dénomination présentée par l'entreprise d'assurance et de réassurance « Axa Assistance » ;",
      "publication_date_hijri": "",
      "publication_date_gregorian": "",
      "page_start": 56,
      "description": "Loi n° 110-14 instituant un régime de couverture des conséquences d'événements catastrophiques ; » La demande d'approbation du projet de modification du règlement de la caisse interne de décès de la Mutuelle Générale du Personnel des Administrations Publiques (MGPAP) ; » Le projet d'amendement de l'arrêté pris en application du livre II du code des assurances ; » La demande de changement de dénomination présentée par l'entreprise d'assurance et de réassurance « Axa Assistance » ;, d'un montant de 22,00 dirhams",
      "signatories": [],
      "content_details": {
        "loan_guarantee": {
          "amount": 22.0,
          "currency": "D"
        }
      }
    },
    {
      "type": "Loi",
      "number": "",
      "title": "55-19 du 6 mars 2020 relative à la simplification des procédures et des formalités administratives",
      "publication_date_hijri": "",
      "publication_date_gregorian": "",
      "page_start": 58,
      "description": "Loi 55-19 du 6 mars 2020 relative à la simplification des procédures et des formalités administratives, d'un montant de 19,00 dirhams",
      "signatories": [],
      "content_details": {
        "loan_guarantee": {
          "amount": 19.0,
          "currency": "D"
        }
      }
    },
    {
      "type": "Loi",
      "number": "54-23",
      "title": "modifiant et complétant la",
      "publication_date_hijri": "",
      "publication_date_gregorian": "",
      "page_start": 58,
      "description": "Loi n° 54-23 modifiant et complétant la",
      "signatories": []
    },
    {
      "type": "Loi",
      "number": "65-00",
      "title": "précitée, relatif à la séparation des activités d'assurance",
      "publication_date_hijri": "",
      "publication_date_gregorian": "",
      "page_start": 62,
      "description": "Loi n° 65-00 précitée, relatif à la séparation des activités d'assurance, d'un montant de 63,00 dirhams, au profit de Office Marocain de la",
      "signatories": [],
      "content_details": {
        "loan_guarantee": {
          "amount": 63.0,
          "currency": "D",
          "beneficiary": "Office Marocain de la"
        }
      }
    },
    {
      "type": "Loi",
      "number": "41-23",
      "title": "portant annulation des créances dues à la Caisse nationale de sécurité sociale au titre de l'assurance maladie obligatoire de base, relatives aux cotisations, majorations, frais de poursuites et amendes, dues par les catégories de professionnels, travailleurs indépendants et les personnes non-salariées exerçant une activité libérale, promulguée par le dahir n° 1-23-86 du 30 novembre 2023",
      "publication_date_hijri": "",
      "publication_date_gregorian": "",
      "page_start": 102,
      "description": "Loi n° 41-23 portant annulation des créances dues à la Caisse nationale de sécurité sociale au titre de l'assurance maladie obligatoire de base, relatives aux cotisations, majorations, frais de poursuites et amendes, dues par les catégories de professionnels, travailleurs indépendants et les personnes non-salariées exerçant une activité libérale, promulguée par le dahir n° 1-23-86 du 30 novembre 2023, d'un montant de 86,00 dirhams",
      "signatories": [],
      "content_details": {
        "loan_guarantee": {
          "amount": 86.0,
          "currency": "D"
        }
      }
    },
    {
      "type": "Loi",
      "number": "98-15",
      "title": "relative au régime de l'assurance",
      "publication_date_hijri": "",
      "publication_date_gregorian": "",
      "page_start": 60,
      "description": "Loi n° 98-15 relative au régime de l'assurance",
      "signatories": []
    },
    {
      "type": "Loi",
      "number": "99-15",
      "title": "instituant un régime de",
      "publication_date_hijri": "",
      "publication_date_gregorian": "",
      "page_start": 60,
      "description": "Loi n° 99-15 instituant un régime de",
      "signatories": []
    },
    {
      "type": "Décret",
      "number": "2-18-622",
      "title": "du 17 janvier 2019",
      "publication_date_hijri": "",
      "publication_date_gregorian": "",
      "page_start": 60,
      "description": "Décret n° 2-18-622 du 17 janvier 2019, d'un montant de 622,00 dirhams",
      "signatories": [],
      "content_details": {
        "loan_guarantee": {
          "amount": 622.0,
          "currency": "D"
        }
      }
    },
    {
      "type": "Décret",
      "number": "2-23-690",
      "title": "portant application de la",
      "publication_date_hijri": "",
      "publication_date_gregorian": "",
      "page_start": 60,
      "description": "Décret n° 2-23-690 portant application de la",
      "signatories": []
    },
    {
      "type": "Loi",
      "number": "60-22",
      "title": "relative au régime d'assurance maladie obligatoire de base des personnes capables de s'acquitter de leurs cotisations et n'exerçant aucune activité rémunérée ou non rémunérée, promulguée par le dahir n° 1-23-41 du 25 mai 2023",
      "publication_date_hijri": "",
      "publication_date_gregorian": "",
      "page_start": 100,
      "description": "Loi n° 60-22 relative au régime d'assurance maladie obligatoire de base des personnes capables de s'acquitter de leurs cotisations et n'exerçant aucune activité rémunérée ou non rémunérée, promulguée par le dahir n° 1-23-41 du 25 mai 2023, d'un montant de 41,00 dirhams",
      "signatories": [],
      "content_details": {
        "loan_guarantee": {
          "amount": 41.0,
          "currency": "D"
        }
      }
    },
    {
      "type": "Loi",
      "number": "43-05",
      "title": "dans le processus de mise en œuvre du dispositif LBC/FT",
      "publication_date_hijri": "",
      "publication_date_gregorian": "",
      "page_start": 76,
      "description": "Loi n° 43-05 dans le processus de mise en œuvre du dispositif LBC/FT, d'un montant de 5,00 dirhams",
      "signatories": [],
      "content_details": {
        "loan_guarantee": {
          "amount": 5.0,
          "currency": "D",
          "beneficiary": "Ministère de l"
        }
      }
    },
    {
      "type": "Loi",
      "number": "09-08",
      "title": "relative à la protection",
      "publication_date_hijri": "",
      "publication_date_gregorian": "",
      "page_start": 80,
      "description": "Loi n° 09-08 relative à la protection, d'un montant de 81,00 dirhams",
      "signatories": [
        {
          "name": "CHARGES DE PERSONNEL",
          "title": ""
        },
        {
          "name": "AUTRES CHARGES EXTERNES",
          "title": ""
        },
        {
          "name": "CHARGES NON COURANTES",
          "title": ""
        }
      ],
      "content_details": {
        "loan_guarantee": {
          "amount": 81.0,
          "currency": "D"
        }
      }
    },
    {
      "type": "Décret",
      "number": "2-23-24",
      "title": "23 janvier 2023 modifiant le",
      "publication_date_hijri": "",
      "publication_date_gregorian": "",
      "page_start": 100,
      "description": "Décret n° 2-23-24 23 janvier 2023 modifiant le, d'un montant de 24,00 dirhams",
      "signatories": [],
      "content_details": {
        "loan_guarantee": {
          "amount": 24.0,
          "currency": "D"
        }
      }
    },
    {
      "type": "Décret",
      "number": "2-21-288",
      "title": "du 30 avril 2021",
      "publication_date_hijri": "",
      "publication_date_gregorian": "",
      "page_start": 100,
      "description": "Décret n° 2-21-288 du 30 avril 2021, d'un montant de 288,00 dirhams",
      "signatories": [],
      "content_details": {
        "loan_guarantee": {
          "amount": 288.0,
          "currency": "D"
        }
      }
    },
    {
      "type": "Décret",
      "number": "2-22-385",
      "title": "du 8 mai 2023 fixant la liste des actes",
      "publication_date_hijri": "",
      "publication_date_gregorian": "",
      "page_start": 100,
      "description": "Décret n° 2-22-385 du 8 mai 2023 fixant la liste des actes, d'un montant de 385,00 dirhams",
      "signatories": [],
      "content_details": {
        "loan_guarantee": {
          "amount": 385.0,
          "currency": "D"
        }
      }
    },
    {
      "type": "Décret",
      "number": "2-22-386",
      "title": "du 8 mai 2023 fixant la liste des actes",
      "publication_date_hijri": "",
      "publication_date_gregorian": "",
      "page_start": 100,
      "description": "Décret n° 2-22-386 du 8 mai 2023 fixant la liste des actes, d'un montant de 386,00 dirhams",
      "signatories": [],
      "content_details": {
        "loan_guarantee": {
          "amount": 386.0,
          "currency": "D"
        }
      }
    },
    {
      "type": "Loi",
      "number": "",
      "title": "n99-17° portant code des assurances Le 7 septembre 2023 Publication au Bulletin Officiel n° 7228 de la",
      "publication_date_hijri": "",
      "publication_date_gregorian": "",
      "page_start": 102,
      "description": "Loi n99-17° portant code des assurances Le 7 septembre 2023 Publication au Bulletin Officiel n° 7228 de la, d'un montant de 7.228,00 dirhams",
      "signatories": [],
      "content_details": {
        "loan_guarantee": {
          "amount": 7228.0,
          "currency": "D"
        }
      }
    },
    {
      "type": "Loi",
      "number": "39-22",
      "title": "modifiant et complétant le dahir n° 1-57-187 du 12 novembre 1963 portant statut de la mutualité, promulguée par le dahir n° 1-23-59 du 10 août 2023",
      "publication_date_hijri": "",
      "publication_date_gregorian": "",
      "page_start": 102,
      "description": "Loi n° 39-22 modifiant et complétant le dahir n° 1-57-187 du 12 novembre 1963 portant statut de la mutualité, promulguée par le dahir n° 1-23-59 du 10 août 2023, d'un montant de 187,00 dirhams",
      "signatories": [],
      "content_details": {
        "loan_guarantee": {
          "amount": 187.0,
          "currency": "D"
        }
      }
    },
    {
      "type": "Loi",
      "number": "58-23",
      "title": "relative au régime de l'aide sociale directe,",
      "publication_date_hijri": "",
      "publication_date_gregorian": "",
      "page_start": 102,
      "description": "Loi n° 58-23 relative au régime de l'aide sociale directe,, d'un montant de 87,00 dirhams",
      "signatories": [],
      "content_details": {
        "loan_guarantee": {
          "amount": 87.0,
          "currency": "D"
        }
      }
    },
    {
      "type": "Loi",
      "number": "07-22",
      "title": "portant création de la Haute autorité de la santé, promulguée par le dahir n° 1-23-84 du 30 novembre 2023 ; •",
      "publication_date_hijri": "",
      "publication_date_gregorian": "",
      "page_start": 102,
      "description": "Loi n° 07-22 portant création de la Haute autorité de la santé, promulguée par le dahir n° 1-23-84 du 30 novembre 2023 ; •, d'un montant de 84,00 dirhams",
      "signatories": [],
      "content_details": {
        "loan_guarantee": {
          "amount": 84.0,
          "currency": "D"
        }
      }
    },
    {
      "type": "Loi",
      "number": "1799",
      "title": "portant code des assurances et des lois régissant les régimes de retraite obligatoires, la Caisse Nationale de Retraites et d'Assurances (CNRA) et l'Assurance Maladie Obligatoire de base (AMO) (",
      "publication_date_hijri": "",
      "publication_date_gregorian": "",
      "page_start": 102,
      "description": "Loi n° 1799 portant code des assurances et des lois régissant les régimes de retraite obligatoires, la Caisse Nationale de Retraites et d'Assurances (CNRA) et l'Assurance Maladie Obligatoire de base (AMO) (",
      "signatories": []
    },
    {
      "type": "Loi",
      "number": "64",
      "title": ".12 portant création de l'Autorité",
      "publication_date_hijri": "",
      "publication_date_gregorian": "",
      "page_start": 108,
      "description": "Loi n° 64 .12 portant création de l'Autorité, d'un montant de 31,00 dirhams",
      "signatories": [],
      "content_details": {
        "loan_guarantee": {
          "amount": 31.0,
          "currency": "D"
        }
      }
    },
    {
      "type": "Loi",
      "number": "1-84-7",
      "title": "du 6 rabii II 1404 (10 janvier 1984) édictant des mesures d'ordre financier en attendant la promulgation de la loi de finances pour l'année 1984 ; » Les plans de rétablissement et les plans de redressement présentés par les organismes de retraite en application respectivement des articles 117 et 119 de la",
      "publication_date_hijri": "",
      "publication_date_gregorian": "",
      "page_start": 110,
      "description": "Loi n° 1-84-7 du 6 rabii II 1404 (10 janvier 1984) édictant des mesures d'ordre financier en attendant la promulgation de la loi de finances pour l'année 1984 ; » Les plans de rétablissement et les plans de redressement présentés par les organismes de retraite en application respectivement des articles 117 et 119 de la, d'un montant de 7,00 dirhams",
      "signatories": [],
      "content_details": {
        "loan_guarantee": {
          "amount": 7.0,
          "currency": "D"
        }
      }
    },
    {
      "type": "Décret",
      "number": "",
      "title": "n° 2-23-1 du 25 rejeb 1444 (16 février 2023) 80 Arrêté du Chef du gouvernement n° 3-13-23 du 8 chaabane 1444 (1er mars 2023) pris pour l'application de l'article 6 du",
      "publication_date_hijri": "",
      "publication_date_gregorian": "",
      "page_start": 140,
      "description": "Décret n° 2-23-1 du 25 rejeb 1444 (16 février 2023) 80 Arrêté du Chef du gouvernement n° 3-13-23 du 8 chaabane 1444 (1er mars 2023) pris pour l'application de l'article 6 du, d'un montant de 1,00 dirhams",
      "signatories": [],
      "content_details": {
        "loan_guarantee": {
          "amount": 1.0,
          "currency": "D"
        }
      }
    },
    {
      "type": "Décret",
      "number": "2-23-1",
      "title": "25 rejeb 1444 (16 février 2023) relatif à la mise en œuvre du dispositif de soutien principal à l'investissement et du dispositif de soutien spécifique applicable aux projets d'investissement à caractère stratégique",
      "publication_date_hijri": "",
      "publication_date_gregorian": "",
      "page_start": 140,
      "description": "Décret n° 2-23-1 25 rejeb 1444 (16 février 2023) relatif à la mise en œuvre du dispositif de soutien principal à l'investissement et du dispositif de soutien spécifique applicable aux projets d'investissement à caractère stratégique, d'un montant de 1,00 dirhams, pour le financement du Projet « : Imagerie Satellite Data Mining et Applications Agricoles (ISA) »",
      "signatories": [],
      "content_details": {
        "loan_guarantee": {
          "amount": 1.0,
          "currency": "D",
          "beneficiary": "Ministère de la transition",
          "project": ": Imagerie Satellite Data Mining et Applications Agricoles (ISA)"
        }
      }
    }
  ]
}